CHANGELOG.md
ree_connector/__init__.py
ree_connector/markets.py
ree_connector/objects.py
ree_connector/utils.py
ree_connector-0.1.3.dist-info/LICENSE
ree_connector-0.1.3.dist-info/WHEEL
ree_connector-0.1.3.dist-info/METADATA
ree_connector-0.1.3.dist-info/RECORD
