Metadata-Version: 2.1
Name: ree-connector
Version: 0.1.3
Summary: Lightweight package to consume data from REE (Red Eléctrica de España)
License: MIT
Keywords: Python,Energy,Tools,IoT,Domotics
Author: Jorge Marín
Author-email: jormarcor@alum.us.es
Requires-Python: >=3.6,<4.0
Classifier: License :: OSI Approved :: MIT License
Classifier: Operating System :: OS Independent
Classifier: Programming Language :: Python :: 3
Classifier: Programming Language :: Python :: 3.10
Classifier: Programming Language :: Python :: 3.6
Classifier: Programming Language :: Python :: 3.7
Classifier: Programming Language :: Python :: 3.8
Classifier: Programming Language :: Python :: 3.9
Classifier: Topic :: Software Development :: Libraries :: Python Modules
Requires-Dist: requests (>=2.26.0,<3.0.0)
Project-URL: Documentation, https://jorgemarin.gitlab.io/ree-connector/
